CHANGELOG
INSTALL
MANIFEST.in
PKG-INFO
README.txt
setup.cfg
setup.py
bash_completion.d/scivm
doc/COPYING.LESSER
doc/LICENSE
doc/scivm.1
scicloud.egg-info/PKG-INFO
scicloud.egg-info/SOURCES.txt
scicloud.egg-info/dependency_links.txt
scicloud.egg-info/entry_points.txt
scicloud.egg-info/requires.txt
scicloud.egg-info/top_level.txt
scicloud.egg.info/PKG-INFO
sciscicloud.egg-info/PKG-INFO
src/__init__.py
src/_server_bucket.py
src/account.py
src/bucket.py
src/cloud.py
src/cloudconfig.py
src/cloudinterface.py
src/cloudlog.py
src/cron.py
src/environment.py
src/files.py
src/mp.py
src/pool_interface.py
src/queue.py
src/realtime.py
src/rest.py
src/shell.py
src/versioninfo.py
src/volume.py
src/wait_for.py
src/cli/__init__.py
src/cli/argparse.py
src/cli/argparsers.py
src/cli/functions.py
src/cli/main.py
src/cli/setup_machine.py
src/cli/util.py
src/serialization/__init__.py
src/serialization/cloudpickle.py
src/serialization/pickledebug.py
src/serialization/report.py
src/serialization/serializationhandlers.py
src/serialization/xmlhandlers.py
src/shortcuts/__init__.py
src/shortcuts/ssh.py
src/transport/__init__.py
src/transport/adapter.py
src/transport/codedependency.py
src/transport/connection.py
src/transport/local.py
src/transport/network.py
src/transport/queue_attachment.py
src/transport/simulator.py
src/util/__init__.py
src/util/cache.py
src/util/common.py
src/util/configmanager.py
src/util/credentials.py
src/util/cronexpr.py
src/util/gzip_stream.py
src/util/template.py
src/util/urllib2_file.py
src/util/writeconfig.py
src/util/xrange_helper.py
src/util/zip_packer.py
src/util/cloghandler/LICENSE
src/util/cloghandler/PKG-INFO
src/util/cloghandler/README
src/util/cloghandler/__init__.py
src/util/cloghandler/cloghandler.py
src/util/cloghandler/portalocker.py