Metadata-Version: 1.1
Name: scicloud
Version: 3.0.4
Summary: Science VM client-side library
Home-page: http://www.scivm.com
Author: Science Automation, Inc.
Author-email: contact@scivm.com
License: GNU LGPL
Platform: CPython 2.6
Platform: CPython 2.7
Classifier: Development Status :: 5 - Production/Stable
Classifier: Intended Audience :: Developers
Classifier: License :: OSI Approved :: GNU Library or Lesser General Public License (LGPL)
Classifier: Operating System :: POSIX
Classifier: Operating System :: Microsoft :: Windows
Classifier: Operating System :: MacOS :: MacOS X
Classifier: Programming Language :: Python :: 2.6
Classifier: Programming Language :: Python :: 2.7
Classifier: Topic :: Software Development :: Libraries :: Python Modules
Classifier: Topic :: System :: Distributed Computing
Classifier: Topic :: System :: Networking
